LICENSE
MANIFEST.in
README.rst
setup.cfg
setup.py
src/diff_highlight.py
src/diff_hilite.egg-info/PKG-INFO
src/diff_hilite.egg-info/SOURCES.txt
src/diff_hilite.egg-info/dependency_links.txt
src/diff_hilite.egg-info/entry_points.txt
src/diff_hilite.egg-info/requires.txt
src/diff_hilite.egg-info/top_level.txt
src/highlights/__init__.py
src/highlights/command.py
src/highlights/pprint.py