Metadata-Version: 2.1
Name: diff-hilite
Version: 2.0
Summary: Diff wrapper/filter for intra-line changes highlighting
Home-page: https://github.com/pfalcon/diff-hilite
Author: Takeshi Komiya
Author-email: i.tkomiya at gmail.com
Maintainer: Paul Sokolovsky
Maintainer-email: pfalcon@users.sourceforge.net
License: Apache License 2.0
Keywords: git,diff,intra-line,intraline,highlight
Platform: UNKNOWN
Classifier: Development Status :: 5 - Production/Stable
Classifier: Intended Audience :: System Administrators
Classifier: License :: OSI Approved :: Apache Software License
Classifier: Programming Language :: Python
Classifier: Programming Language :: Python :: 2.6
Classifier: Programming Language :: Python :: 2.7
Classifier: Programming Language :: Python :: 3.2
Classifier: Programming Language :: Python :: 3.3
Classifier: Programming Language :: Python :: 3.4
Classifier: Programming Language :: Python :: 3.5
Classifier: Topic :: Software Development
Classifier: Topic :: Software Development :: Version Control
Classifier: Topic :: Text Processing :: Filters
Provides-Extra: testing
